dronesim/__init__.py
dronesim/client.py
dronesim/pfm.py
dronesim/types.py
dronesim/utils.py
DroneSim-0.2.dist-info/METADATA
DroneSim-0.2.dist-info/WHEEL
DroneSim-0.2.dist-info/top_level.txt
DroneSim-0.2.dist-info/RECORD
